README.md
setup.py
src/guozhi.egg-info/PKG-INFO
src/guozhi.egg-info/SOURCES.txt
src/guozhi.egg-info/dependency_links.txt
src/guozhi.egg-info/not-zip-safe
src/guozhi.egg-info/requires.txt
src/guozhi.egg-info/top_level.txt
src/juice/MqttClient.py
src/juice/__init__.py
src/juice/exception/IotException.py
src/juice/exception/__init__.py
src/juice/handler/PropHandler.py
src/juice/handler/SysHandler.py
src/juice/handler/TaskHandler.py
src/juice/handler/__init__.py
src/juice/handler/extend/__init__.py
src/juice/handler/extend/device/SysGpioHandler.py
src/juice/handler/extend/device/SysPropHandler.py
src/juice/handler/extend/device/__init__.py
src/juice/handler/extend/sensor/SensorGetHandler.py
src/juice/handler/extend/sensor/SensorSetHandler.py
src/juice/handler/extend/sensor/__init__.py
src/juice/model/JuiceMessage.py
src/juice/model/ReplyMessage.py
src/juice/model/__init__.py
src/juice/util/Const.py
src/juice/util/GpioUtil.py
src/juice/util/ReadJson.py
src/juice/util/Util.py
src/juice/util/__init__.py