Metadata-Version: 2.1
Name: guozhi
Version: 0.1.6
Summary: python-iot-sdk for guozhiyun
Home-page: https://gitee.com/cui_com/jucie-python-sdk.git
Author: yebing
Author-email: cui_com@qq.com
Maintainer-email: cui_com@qq.com
License: UNKNOWN
Platform: UNKNOWN
